postgresql_singleton/__init__.py
postgresql_singleton/config.py
postgresql_singleton/db.py
tests/__init__.py
tests/test_postgresql.py
postgresql_singleton-0.1.2.dist-info/METADATA
postgresql_singleton-0.1.2.dist-info/WHEEL
postgresql_singleton-0.1.2.dist-info/top_level.txt
postgresql_singleton-0.1.2.dist-info/RECORD
