Metadata-Version: 2.1
Name: postgresql-singleton
Version: 0.1.2
Summary: PostgreSQL Singleton connection pool manager
Home-page: https://github.com/alkaline2018/postgresql-singleton
Author: Song Seung Hwan
Author-email: shdth117@gmail.com
Classifier: Programming Language :: Python :: 3
Classifier: License :: OSI Approved :: MIT License
Classifier: Operating System :: OS Independent
Requires-Python: >=3.6
Requires-Dist: psycopg2-binary
